{
    "keep": {
        "days": true,
        "amount": 1
    },
    "auditLog": "C:\\Users\\marku\\OneDrive\\Dokumente\\markus_data\\Private Daten\\Software Development\\3.Project\\3.1 Visual_Studio_Projects\\OEE_Event_Driven II\\backend\\logs\\.1ac635e983428167b1035738d0e6c8e660171cdc-audit.json",
    "files": [
        {
            "date": 1733945686731,
            "name": "C:\\Users\\marku\\OneDrive\\Dokumente\\markus_data\\Private Daten\\Software Development\\3.Project\\3.1 Visual_Studio_Projects\\OEE_Event_Driven II\\backend\\logs\\rejections-2024-12-11.log",
            "hash": "3a4b9a5e5635bb8c406537d06e2eebd09d20c57520c735dee0d5666ece848392"
        }
    ],
    "hashType": "sha256"
}